dadosneurais/__init__.py
dadosneurais/my_fat.py
fat/__init__.py
fat/my_fat.py
dadosneurais-0.0.2.dist-info/METADATA
dadosneurais-0.0.2.dist-info/WHEEL
dadosneurais-0.0.2.dist-info/top_level.txt
dadosneurais-0.0.2.dist-info/RECORD
