Metadata-Version: 2.1
Name: dadosneurais
Version: 0.0.2
Summary: calc the number factorial
Author: Seu Nome
Classifier: Programming Language :: Python :: 3
Classifier: License :: OSI Approved :: MIT License
Classifier: Operating System :: OS Independent
Requires-Python: >=3.6
